LICENSE
README.md
nautobot_chatops_ipfabric/__init__.py
nautobot_chatops_ipfabric/api/__init__.py
nautobot_chatops_ipfabric/context.py
nautobot_chatops_ipfabric/ipfabric_wrapper.py
nautobot_chatops_ipfabric/migrations/__init__.py
nautobot_chatops_ipfabric/static/ipfabric/IP_Fabric_logo_small.jpg
nautobot_chatops_ipfabric/static/ipfabric/ipfabric_logo.png
nautobot_chatops_ipfabric/tests/__init__.py
nautobot_chatops_ipfabric/tests/test_api.py
nautobot_chatops_ipfabric/tests/test_basic.py
nautobot_chatops_ipfabric/urls.py
nautobot_chatops_ipfabric/utils.py
nautobot_chatops_ipfabric/worker.py
nautobot_chatops_ipfabric-3.0.1.dist-info/entry_points.txt
nautobot_chatops_ipfabric-3.0.1.dist-info/METADATA
nautobot_chatops_ipfabric-3.0.1.dist-info/WHEEL
nautobot_chatops_ipfabric-3.0.1.dist-info/LICENSE
nautobot_chatops_ipfabric-3.0.1.dist-info/RECORD
