Metadata-Version: 2.1
Name: nautobot-chatops-ipfabric
Version: 3.0.1
Summary: Nautobot Plugin Chatops IPFabric
Home-page: https://github.com/networktocode-llc/nautobot-chatops-extension-ipfabric
License: Apache-2.0
Keywords: nautobot,nautobot-plugin,nautobot-chatops-plugin
Author: Network to Code, LLC
Author-email: info@networktocode.com
Requires-Python: >=3.7.1,<4.0.0
Classifier: License :: OSI Approved :: Apache Software License
Classifier: Programming Language :: Python :: 3
Classifier: Programming Language :: Python :: 3.8
Classifier: Programming Language :: Python :: 3.9
Classifier: Programming Language :: Python :: 3.10
Classifier: Programming Language :: Python :: 3.11
Requires-Dist: ipfabric (>=6.0.9,<6.1.0)
Requires-Dist: ipfabric-diagrams (>=6.0.2,<6.1.0)
Requires-Dist: nautobot-chatops (>=1.1.0,<2.0.0)
Requires-Dist: netutils (>=1.0.0,<2.0.0)
Project-URL: Repository, https://github.com/networktocode-llc/nautobot-chatops-extension-ipfabric
